{"data":{"site":{"siteMetadata":{"title":"Kingso's blog","subtitle":"Kingso's blog"}},"allMarkdownRemark":{"edges":[{"node":{"fields":{"slug":"/posts/20190902-TIL/","categorySlug":"/category/til/"},"frontmatter":{"title":"[20190902-TIL]","date":"2019-09-02T14:00:00.169Z","category":"TIL","description":"position / 미들웨어"}}}]}},"pageContext":{"isCreatedByStatefulCreatePages":false,"tag":"position","currentPage":0,"postsLimit":5,"postsOffset":0,"prevPagePath":"/tag/position","nextPagePath":"/tag/position/page/1","hasPrevPage":false,"hasNextPage":false}}