{"data":{"site":{"siteMetadata":{"author":{"name":"Kingso","contacts":{"twitter":"#"}},"disqusShortname":"kingsoblog","subtitle":"Kingso's blog","title":"Kingso's blog","url":"https://kingso.netlify.com"}},"markdownRemark":{"id":"a3d6f87c-fcf7-530f-addf-58c99f021fad","html":"<br>\n<h2 id=\"2019-09-04-til\"><a href=\"#2019-09-04-til\" aria-label=\"2019 09 04 til permalink\" class=\"anchor\"><svg aria-hidden=\"true\" focusable=\"false\" height=\"16\" version=\"1.1\" viewBox=\"0 0 16 16\" width=\"16\"><path fill-rule=\"evenodd\" d=\"M4 9h1v1H4c-1.5 0-3-1.69-3-3.5S2.55 3 4 3h4c1.45 0 3 1.69 3 3.5 0 1.41-.91 2.72-2 3.25V8.59c.58-.45 1-1.27 1-2.09C10 5.22 8.98 4 8 4H4c-.98 0-2 1.22-2 2.5S3 9 4 9zm9-3h-1v1h1c1 0 2 1.22 2 2.5S13.98 12 13 12H9c-.98 0-2-1.22-2-2.5 0-.83.42-1.64 1-2.09V6.25c-1.09.53-2 1.84-2 3.25C6 11.31 7.55 13 9 13h4c1.45 0 3-1.69 3-3.5S14.5 6 13 6z\"></path></svg></a>2019-09-04 TIL</h2>\n<br>\n<h2 id=\"잘-알려지지-않은-유용한-css-속성-알아보기\"><a href=\"#%EC%9E%98-%EC%95%8C%EB%A0%A4%EC%A7%80%EC%A7%80-%EC%95%8A%EC%9D%80-%EC%9C%A0%EC%9A%A9%ED%95%9C-css-%EC%86%8D%EC%84%B1-%EC%95%8C%EC%95%84%EB%B3%B4%EA%B8%B0\" aria-label=\"잘 알려지지 않은 유용한 css 속성 알아보기 permalink\" class=\"anchor\"><svg aria-hidden=\"true\" focusable=\"false\" height=\"16\" version=\"1.1\" viewBox=\"0 0 16 16\" width=\"16\"><path fill-rule=\"evenodd\" d=\"M4 9h1v1H4c-1.5 0-3-1.69-3-3.5S2.55 3 4 3h4c1.45 0 3 1.69 3 3.5 0 1.41-.91 2.72-2 3.25V8.59c.58-.45 1-1.27 1-2.09C10 5.22 8.98 4 8 4H4c-.98 0-2 1.22-2 2.5S3 9 4 9zm9-3h-1v1h1c1 0 2 1.22 2 2.5S13.98 12 13 12H9c-.98 0-2-1.22-2-2.5 0-.83.42-1.64 1-2.09V6.25c-1.09.53-2 1.84-2 3.25C6 11.31 7.55 13 9 13h4c1.45 0 3-1.69 3-3.5S14.5 6 13 6z\"></path></svg></a>잘 알려지지 않은 유용한 CSS 속성 알아보기</h2>\n<p>[ 출처: https://ahnheejong.name/articles/less-famous-css-properties/ ]</p>\n<br>\n<h2 id=\"코드-스플리팅\"><a href=\"#%EC%BD%94%EB%93%9C-%EC%8A%A4%ED%94%8C%EB%A6%AC%ED%8C%85\" aria-label=\"코드 스플리팅 permalink\" class=\"anchor\"><svg aria-hidden=\"true\" focusable=\"false\" height=\"16\" version=\"1.1\" viewBox=\"0 0 16 16\" width=\"16\"><path fill-rule=\"evenodd\" d=\"M4 9h1v1H4c-1.5 0-3-1.69-3-3.5S2.55 3 4 3h4c1.45 0 3 1.69 3 3.5 0 1.41-.91 2.72-2 3.25V8.59c.58-.45 1-1.27 1-2.09C10 5.22 8.98 4 8 4H4c-.98 0-2 1.22-2 2.5S3 9 4 9zm9-3h-1v1h1c1 0 2 1.22 2 2.5S13.98 12 13 12H9c-.98 0-2-1.22-2-2.5 0-.83.42-1.64 1-2.09V6.25c-1.09.53-2 1.84-2 3.25C6 11.31 7.55 13 9 13h4c1.45 0 3-1.69 3-3.5S14.5 6 13 6z\"></path></svg></a>코드 스플리팅</h2>\n<p>싱글 페이지 애플리케이션의 단점은 페이지 로딩 속도가 지연될 수 있다는 점입니다. 로딩 속도가 지연되는 이유는 자바스크립트 번들 파일에 모든 애플리케이션의 로직을 불러오므로 규모가 커지면서 용량도 커지기 때문입니다.</p>\n<p>코드 스플리팅은 말 그대로 코드를 분할한다는 의미입니다.\nwebpack에서 프로젝트를 번들링할 때 파일 하나가 아니라 파일 여러 개로 분리시켜서 결과물을 만들 수 있습니다.\n또 페이지를 로딩할 때 한꺼번에 불러오는 것이 아니라 필요한 시점에 불러올 수도 있습니다.</p>\n<br>\n<h2 id=\"koa-프레임워크\"><a href=\"#koa-%ED%94%84%EB%A0%88%EC%9E%84%EC%9B%8C%ED%81%AC\" aria-label=\"koa 프레임워크 permalink\" class=\"anchor\"><svg aria-hidden=\"true\" focusable=\"false\" height=\"16\" version=\"1.1\" viewBox=\"0 0 16 16\" width=\"16\"><path fill-rule=\"evenodd\" d=\"M4 9h1v1H4c-1.5 0-3-1.69-3-3.5S2.55 3 4 3h4c1.45 0 3 1.69 3 3.5 0 1.41-.91 2.72-2 3.25V8.59c.58-.45 1-1.27 1-2.09C10 5.22 8.98 4 8 4H4c-.98 0-2 1.22-2 2.5S3 9 4 9zm9-3h-1v1h1c1 0 2 1.22 2 2.5S13.98 12 13 12H9c-.98 0-2-1.22-2-2.5 0-.83.42-1.64 1-2.09V6.25c-1.09.53-2 1.84-2 3.25C6 11.31 7.55 13 9 13h4c1.45 0 3-1.69 3-3.5S14.5 6 13 6z\"></path></svg></a>Koa 프레임워크</h2>\n<p>Node.js 환경에서 웹 서버를 구축할 때는 보통 Express, Hapi, Koa 등 웹 프레임워크를 사용합니다.</p>\n<p>현재 웹 프레임워크 중에서 Express가 가장 사용률이 높기는 합니다.\n하지만 이 프레임워크는 오픈 소스의 소유권이 IBM 계열사인 StringLoop로 이전되어 유지 보수는 하고 있지만 인지도는 조금씩 잃고 있습니다.</p>\n<p>Koa 프레임워크는 Express의 기존 개발 팀이 소유권을 IBM에 넘기기 전부터 개발해 오던 프로젝트로, Express를 리팩토링한 결과물이며, 기존 Express에 비해 아키텍처가 많이 바뀌어서 버전을 높이지 않고 새 이름을 붙였다고 합니다.</p>\n<p>Koa는 Express에 비해 훨씬 가볍고, Node v7.6부터 정식으로 지원하는 async/await 문법을 아주 편하게 사용할 수 있습니다.\n따라서 콜백을 무수하게 사용하는 콜백 지옥을 겪을 일도 없고, 비동기 작업도 편리하게 관리할 수 있습니다.</p>","fields":{"slug":"/posts/20190904-TIL/","tagSlugs":["/tag/css/","/tag/코드-스플리팅/","/tag/koa/"]},"frontmatter":{"date":"2019-09-05T14:00:00.169Z","description":"잘 알려지지 않은 유용한 CSS 속성 / React 코드 스플리팅 / Koa 프레임워크","tags":["CSS","코드 스플리팅","Koa"],"title":"[20190905-TIL]"}}},"pageContext":{"isCreatedByStatefulCreatePages":false,"slug":"/posts/20190904-TIL/"}}