{"data":{"site":{"siteMetadata":{"title":"Kingso's blog","subtitle":"Kingso's blog"}},"allMarkdownRemark":{"edges":[{"node":{"fields":{"slug":"/posts/React4/","categorySlug":"/category/react/"},"frontmatter":{"title":"React - 04","date":"2019-08-01T14:00:00.169Z","category":"React","description":"웹팩(WebPack) 설정하기"}}},{"node":{"fields":{"slug":"/posts/React3/","categorySlug":"/category/react/"},"frontmatter":{"title":"React - 03","date":"2019-07-24T14:00:00.169Z","category":"React","description":"웹팩(WebPack) / 바벨(Babel) 설치하기"}}}]}},"pageContext":{"isCreatedByStatefulCreatePages":false,"tag":"babel","currentPage":0,"postsLimit":5,"postsOffset":0,"prevPagePath":"/tag/babel","nextPagePath":"/tag/babel/page/1","hasPrevPage":false,"hasNextPage":false}}